transforx/__init__.py
transforx/core.py
transforx/utils.py
transforx/engines/__init__.py
transforx/engines/google.py
transforx-1.7.3.dist-info/licenses/LICENSE
transforx-1.7.3.dist-info/METADATA
transforx-1.7.3.dist-info/WHEEL
transforx-1.7.3.dist-info/top_level.txt
transforx-1.7.3.dist-info/RECORD
