Metadata-Version: 2.4
Name: transforx
Version: 1.7.3
Summary: A simple Python translation library using Google Translate.
Home-page: https://github.com/iTs-GoJo/TransforX
Author: Ali-Jafari
Author-email: thealiapi@gmail.com
Requires-Python: >=3.6
License-File: LICENSE
Requires-Dist: requests
Dynamic: author
Dynamic: author-email
Dynamic: description
Dynamic: description-content-type
Dynamic: home-page
Dynamic: license-file
Dynamic: requires-dist
Dynamic: requires-python
Dynamic: summary
